path_imports.py
path_imports-1.1.1.dist-info/METADATA
path_imports-1.1.1.dist-info/WHEEL
path_imports-1.1.1.dist-info/licenses/LICENSE.txt
path_imports-1.1.1.dist-info/RECORD
