Metadata-Version: 2.3
Name: path-imports
Version: 1.1.1
Summary: Import modules from anywhere on the file system.
Project-URL: repository, https://github.com/Aran-Fey/path-imports
Author-email: Aran-Fey <rawing7@gmail.com>
License-File: LICENSE.txt
Requires-Python: >=3.8
